{"externalDocs": {"description": "Graph Documentation", "url": "https://help.sap.com/viewer/product/SAP_GRAPH/PROD"}, "info": {"title": "Equipment", "version": "1", "description": "Equipment."}, "openapi": "3.0.2", "x-sap-shortText": "Equipment.", "x-sap-stateInfo": {"state": "Beta"}, "servers": [{"description": "Sandbox URL", "url": "https://sandbox.api.sap.com/sapgraph"}, {"description": "Production URL", "url": "https://eu10.graph.sap/catalog/sap.graph"}], "tags": [{"name": "Equipment", "description": "Equipment."}], "components": {"schemas": {"sap.graph.Equipment": {"title": "Equipment", "type": "object", "x-sapgraph-root-entity": true, "properties": {"id": {"type": "string", "example": "ABC", "description": "Qualified identifier", "x-sapgraph-key": true}, "createdAt": {"example": "2017-04-13T15:51:04Z", "format": "date-time", "type": "string", "nullable": true, "description": "Date and time the entity was created."}, "changedAt": {"example": "2017-04-13T15:51:04Z", "format": "date-time", "type": "string", "nullable": true, "description": "Date and time the entity was changed last."}, "displayId": {"type": "string", "example": "ABC", "nullable": true, "description": "Display ID."}, "name": {"type": "string", "example": "ABC", "nullable": true, "description": "Name.", "x-sapgraph-immutable": true, "x-sapgraph-localized": true}, "category": {"type": "string", "example": "ABC", "nullable": true, "description": "Category."}, "validFrom": {"example": "2017-04-13", "format": "date", "type": "string", "nullable": true, "description": "Valid from."}, "validTo": {"example": "2017-04-13", "format": "date", "type": "string", "nullable": true, "description": "Valid to."}, "product": {"type": "string", "example": "ABC", "nullable": true, "description": "Product."}, "_product": {"allOf": [{"$ref": "https://eu10.graph.sap/catalog/my-bdg/sap.graph/Product#/components/schemas/sap.graph.Product"}], "nullable": true, "description": "Product."}, "serialNumber": {"type": "string", "example": "ABC", "nullable": true, "description": "Serial number."}, "country": {"type": "string", "example": "ABC", "maxLength": 3, "nullable": true, "description": "Country."}, "_country": {"allOf": [{"$ref": "https://eu10.graph.sap/catalog/my-bdg/sap.graph/Country#/components/schemas/sap.graph.Country"}], "nullable": true, "description": "Country."}, "region": {"type": "string", "example": "ABC", "nullable": true, "description": "Region."}, "city": {"type": "string", "example": "ABC", "nullable": true, "description": "City."}, "postalCode": {"type": "string", "example": "ABC", "nullable": true, "description": "Postal Code."}, "street": {"type": "string", "example": "ABC", "nullable": true, "description": "Street."}, "houseNumber": {"type": "string", "example": "ABC", "nullable": true, "description": "House Number."}, "additionalHouseNumber": {"type": "string", "example": "ABC", "nullable": true, "description": "Additional house number."}, "building": {"type": "string", "example": "ABC", "nullable": true, "description": "Building."}, "floor": {"type": "string", "example": "ABC", "nullable": true, "description": "Floor."}, "room": {"type": "string", "example": "ABC", "nullable": true, "description": "Room."}, "salesOrganization": {"type": "string", "example": "ABC", "nullable": true, "description": "Sales Organization."}, "_salesOrganization": {"allOf": [{"$ref": "https://eu10.graph.sap/catalog/my-bdg/sap.graph/SalesOrganization#/components/schemas/sap.graph.SalesOrganization"}], "nullable": true}, "distributionChannel": {"type": "string", "example": "ABC", "nullable": true, "description": "Distribution Channel."}, "_distributionChannel": {"allOf": [{"$ref": "https://eu10.graph.sap/catalog/my-bdg/sap.graph/DistributionChannel#/components/schemas/sap.graph.DistributionChannel"}], "nullable": true, "description": "Distribution Channel."}, "division": {"type": "string", "example": "ABC", "nullable": true, "description": "Division."}, "_division": {"allOf": [{"$ref": "https://eu10.graph.sap/catalog/my-bdg/sap.graph/Division#/components/schemas/sap.graph.Division"}], "nullable": true, "description": "Division."}, "salesOffice": {"type": "string", "example": "ABC", "nullable": true, "description": "Sales Office."}, "salesGroup": {"type": "string", "example": "ABC", "nullable": true, "description": "Sales Group."}, "warranties": {"items": {"$ref": "#/components/schemas/sap.graph.Equipment_warranties"}, "type": "array", "description": "Warranties."}, "classificationData": {"items": {"$ref": "#/components/schemas/sap.graph.Equipment_classificationData"}, "type": "array"}, "_c4c": {"allOf": [{"$ref": "https://eu10.graph.sap/catalog/my-bdg/sap.c4c/RegisteredProductCollection#/components/schemas/sap.c4c.RegisteredProductCollection"}], "nullable": true}}, "description": "Equipment."}, "sap.graph.Equipment-create": {"title": "Equipment (for create)", "type": "object", "properties": {"id": {"type": "string", "example": "ABC", "description": "Qualified identifier"}, "createdAt": {"example": "2017-04-13T15:51:04Z", "format": "date-time", "type": "string", "nullable": true, "description": "Date and time the entity was created."}, "changedAt": {"example": "2017-04-13T15:51:04Z", "format": "date-time", "type": "string", "nullable": true, "description": "Date and time the entity was changed last."}, "displayId": {"type": "string", "example": "ABC", "nullable": true, "description": "Display ID."}, "name": {"type": "string", "example": "ABC", "nullable": true, "description": "Name."}, "category": {"type": "string", "example": "ABC", "nullable": true, "description": "Category."}, "validFrom": {"example": "2017-04-13", "format": "date", "type": "string", "nullable": true, "description": "Valid from."}, "validTo": {"example": "2017-04-13", "format": "date", "type": "string", "nullable": true, "description": "Valid to."}, "product": {"type": "string", "example": "ABC", "nullable": true, "description": "Product."}, "_product": {"allOf": [{"$ref": "https://eu10.graph.sap/catalog/my-bdg/sap.graph/Product#/components/schemas/sap.graph.Product-create"}], "nullable": true, "description": "Product."}, "serialNumber": {"type": "string", "example": "ABC", "nullable": true, "description": "Serial number."}, "country": {"type": "string", "example": "ABC", "maxLength": 3, "nullable": true, "description": "Country."}, "_country": {"allOf": [{"$ref": "https://eu10.graph.sap/catalog/my-bdg/sap.graph/Country#/components/schemas/sap.graph.Country-create"}], "nullable": true, "description": "Country."}, "region": {"type": "string", "example": "ABC", "nullable": true, "description": "Region."}, "city": {"type": "string", "example": "ABC", "nullable": true, "description": "City."}, "postalCode": {"type": "string", "example": "ABC", "nullable": true, "description": "Postal Code."}, "street": {"type": "string", "example": "ABC", "nullable": true, "description": "Street."}, "houseNumber": {"type": "string", "example": "ABC", "nullable": true, "description": "House Number."}, "additionalHouseNumber": {"type": "string", "example": "ABC", "nullable": true, "description": "Additional house number."}, "building": {"type": "string", "example": "ABC", "nullable": true, "description": "Building."}, "floor": {"type": "string", "example": "ABC", "nullable": true, "description": "Floor."}, "room": {"type": "string", "example": "ABC", "nullable": true, "description": "Room."}, "salesOrganization": {"type": "string", "example": "ABC", "nullable": true, "description": "Sales Organization."}, "_salesOrganization": {"allOf": [{"$ref": "https://eu10.graph.sap/catalog/my-bdg/sap.graph/SalesOrganization#/components/schemas/sap.graph.SalesOrganization-create"}], "nullable": true}, "distributionChannel": {"type": "string", "example": "ABC", "nullable": true, "description": "Distribution Channel."}, "_distributionChannel": {"allOf": [{"$ref": "https://eu10.graph.sap/catalog/my-bdg/sap.graph/DistributionChannel#/components/schemas/sap.graph.DistributionChannel-create"}], "nullable": true, "description": "Distribution Channel."}, "division": {"type": "string", "example": "ABC", "nullable": true, "description": "Division."}, "_division": {"allOf": [{"$ref": "https://eu10.graph.sap/catalog/my-bdg/sap.graph/Division#/components/schemas/sap.graph.Division-create"}], "nullable": true, "description": "Division."}, "salesOffice": {"type": "string", "example": "ABC", "nullable": true, "description": "Sales Office."}, "salesGroup": {"type": "string", "example": "ABC", "nullable": true, "description": "Sales Group."}, "warranties": {"items": {"$ref": "#/components/schemas/sap.graph.Equipment_warranties-create"}, "type": "array", "description": "Warranties."}, "classificationData": {"items": {"$ref": "#/components/schemas/sap.graph.Equipment_classificationData-create"}, "type": "array"}, "_c4c": {"allOf": [{"$ref": "https://eu10.graph.sap/catalog/my-bdg/sap.c4c/RegisteredProductCollection#/components/schemas/sap.c4c.RegisteredProductCollection"}], "nullable": true}}, "required": ["id"], "description": "Equipment."}, "sap.graph.Equipment-update": {"title": "Equipment (for update)", "type": "object", "properties": {"createdAt": {"example": "2017-04-13T15:51:04Z", "format": "date-time", "type": "string", "nullable": true, "description": "Date and time the entity was created."}, "changedAt": {"example": "2017-04-13T15:51:04Z", "format": "date-time", "type": "string", "nullable": true, "description": "Date and time the entity was changed last."}, "displayId": {"type": "string", "example": "ABC", "nullable": true, "description": "Display ID."}, "category": {"type": "string", "example": "ABC", "nullable": true, "description": "Category."}, "validFrom": {"example": "2017-04-13", "format": "date", "type": "string", "nullable": true, "description": "Valid from."}, "validTo": {"example": "2017-04-13", "format": "date", "type": "string", "nullable": true, "description": "Valid to."}, "product": {"type": "string", "example": "ABC", "nullable": true, "description": "Product."}, "serialNumber": {"type": "string", "example": "ABC", "nullable": true, "description": "Serial number."}, "country": {"type": "string", "example": "ABC", "maxLength": 3, "nullable": true, "description": "Country."}, "region": {"type": "string", "example": "ABC", "nullable": true, "description": "Region."}, "city": {"type": "string", "example": "ABC", "nullable": true, "description": "City."}, "postalCode": {"type": "string", "example": "ABC", "nullable": true, "description": "Postal Code."}, "street": {"type": "string", "example": "ABC", "nullable": true, "description": "Street."}, "houseNumber": {"type": "string", "example": "ABC", "nullable": true, "description": "House Number."}, "additionalHouseNumber": {"type": "string", "example": "ABC", "nullable": true, "description": "Additional house number."}, "building": {"type": "string", "example": "ABC", "nullable": true, "description": "Building."}, "floor": {"type": "string", "example": "ABC", "nullable": true, "description": "Floor."}, "room": {"type": "string", "example": "ABC", "nullable": true, "description": "Room."}, "salesOrganization": {"type": "string", "example": "ABC", "nullable": true, "description": "Sales Organization."}, "distributionChannel": {"type": "string", "example": "ABC", "nullable": true, "description": "Distribution Channel."}, "division": {"type": "string", "example": "ABC", "nullable": true, "description": "Division."}, "salesOffice": {"type": "string", "example": "ABC", "nullable": true, "description": "Sales Office."}, "salesGroup": {"type": "string", "example": "ABC", "nullable": true, "description": "Sales Group."}}, "description": "Equipment."}, "sap.graph.Equipment_classificationData": {"title": "Equipment_classificationData", "type": "object", "properties": {"id": {"type": "string", "example": "ABC", "description": "Identifier", "x-sapgraph-key": true}, "class": {"type": "string", "example": "ABC", "nullable": true}, "_class": {"allOf": [{"$ref": "https://eu10.graph.sap/catalog/my-bdg/sap.graph/ClassificationClass#/components/schemas/sap.graph.ClassificationClass"}], "nullable": true}, "classType": {"type": "string", "example": "ABC", "nullable": true}, "characteristic": {"type": "string", "example": "ABC", "nullable": true}, "_characteristic": {"allOf": [{"$ref": "https://eu10.graph.sap/catalog/my-bdg/sap.graph/ClassificationCharacteristic#/components/schemas/sap.graph.ClassificationCharacteristic"}], "nullable": true}, "characteristicValue": {"type": "string", "example": "ABC", "nullable": true}}}, "sap.graph.Equipment_classificationData-create": {"title": "Equipment_classificationData (for create)", "type": "object", "properties": {"_class": {"allOf": [{"$ref": "https://eu10.graph.sap/catalog/my-bdg/sap.graph/ClassificationClass#/components/schemas/sap.graph.ClassificationClass-create"}], "nullable": true}, "_characteristic": {"allOf": [{"$ref": "https://eu10.graph.sap/catalog/my-bdg/sap.graph/ClassificationCharacteristic#/components/schemas/sap.graph.ClassificationCharacteristic-create"}], "nullable": true}}}, "sap.graph.Equipment_classificationData-update": {"title": "Equipment_classificationData (for update)", "type": "object"}, "sap.graph.Equipment_warranties": {"title": "Equipment_warranties", "type": "object", "properties": {"warrantyType": {"type": "string", "example": "ABC", "description": "Warranty type.", "x-sapgraph-key": true}, "warrantyId": {"type": "string", "example": "ABC", "nullable": true, "description": "Warranty ID."}, "startDate": {"example": "2017-04-13", "format": "date", "type": "string", "nullable": true, "description": "Start date."}, "endDate": {"example": "2017-04-13", "format": "date", "type": "string", "nullable": true, "description": "End date."}}}, "sap.graph.Equipment_warranties-create": {"title": "Equipment_warranties (for create)", "type": "object"}, "sap.graph.Equipment_warranties-update": {"title": "Equipment_warranties (for update)", "type": "object"}, "error": {"properties": {"error": {"properties": {"code": {"type": "string"}, "details": {"items": {"properties": {"code": {"type": "string"}, "message": {"type": "string"}, "target": {"type": "string"}}, "required": ["code", "message"], "type": "object"}, "type": "array"}, "innererror": {"description": "The structure of this object is service-specific", "type": "object"}, "message": {"type": "string"}, "target": {"type": "string"}}, "required": ["code", "message"], "type": "object"}}, "required": ["error"], "type": "object"}}, "parameters": {"count": {"description": "Include count of items, see [Count](http://docs.oasis-open.org/odata/odata/v4.01/odata-v4.01-part1-protocol.html#sec_SystemQueryOptioncount)", "in": "query", "name": "$count", "schema": {"type": "boolean"}}, "skip": {"description": "Skip the first n items, see [Paging - Skip](http://docs.oasis-open.org/odata/odata/v4.01/odata-v4.01-part1-protocol.html#sec_SystemQueryOptionskip)", "in": "query", "name": "$skip", "schema": {"minimum": 0, "type": "integer"}}, "top": {"description": "Show only the first n items, see [Paging - Top](http://docs.oasis-open.org/odata/odata/v4.01/odata-v4.01-part1-protocol.html#sec_SystemQueryOptiontop)", "example": 50, "in": "query", "name": "$top", "schema": {"minimum": 0, "type": "integer"}}, "search": {"description": "Search items by search phrases, see [Searching](http://docs.oasis-open.org/odata/odata/v4.01/odata-v4.01-part1-protocol.html#sec_SystemQueryOptionsearch)", "in": "query", "name": "$search", "schema": {"type": "string"}}}, "responses": {"error": {"content": {"application/json": {"schema": {"$ref": "#/components/schemas/error"}}}, "description": "Error"}}, "securitySchemes": {"bearerAuth": {"bearerFormat": "JWT", "description": "To use this API, you need to obtain the Access Token. Please follow steps in the official documentation of Graph.", "scheme": "bearer", "type": "http"}}}, "paths": {"/sap.graph/Equipment": {"get": {"parameters": [{"$ref": "#/components/parameters/top"}, {"$ref": "#/components/parameters/skip"}, {"$ref": "#/components/parameters/search"}, {"in": "query", "name": "$filter", "schema": {"type": "string"}, "description": "Filter items by property values, see [Filtering](http://docs.oasis-open.org/odata/odata/v4.01/odata-v4.01-part1-protocol.html#sec_SystemQueryOptionfilter)"}, {"$ref": "#/components/parameters/count"}, {"description": "Order items by property values, see [Sorting](http://docs.oasis-open.org/odata/odata/v4.01/odata-v4.01-part1-protocol.html#sec_SystemQueryOptionorderby)", "explode": false, "in": "query", "name": "$orderby", "schema": {"items": {"enum": ["id", "id desc", "createdAt", "createdAt desc", "changedAt", "changedAt desc", "displayId", "displayId desc", "name", "name desc", "category", "category desc", "validFrom", "validFrom desc", "validTo", "validTo desc", "product", "product desc", "serialNumber", "serialNumber desc", "country", "country desc", "region", "region desc", "city", "city desc", "postalCode", "postalCode desc", "street", "street desc", "houseNumber", "houseNumber desc", "additionalHouseNumber", "additionalHouseNumber desc", "building", "building desc", "floor", "floor desc", "room", "room desc", "salesOrganization", "salesOrganization desc", "distributionChannel", "distributionChannel desc", "division", "division desc", "salesOffice", "salesOffice desc", "salesGroup", "salesGroup desc"], "type": "string"}, "type": "array", "uniqueItems": true}}, {"description": "Select properties to be returned, see [Select](http://docs.oasis-open.org/odata/odata/v4.01/odata-v4.01-part1-protocol.html#sec_SystemQueryOptionselect)", "explode": false, "in": "query", "name": "$select", "schema": {"items": {"enum": ["id", "createdAt", "changedAt", "displayId", "name", "category", "validFrom", "validTo", "product", "serialNumber", "country", "region", "city", "postalCode", "street", "houseNumber", "additionalHouseNumber", "building", "floor", "room", "salesOrganization", "distributionChannel", "division", "salesOffice", "salesGroup"], "type": "string"}, "type": "array", "uniqueItems": true}}, {"description": "Expand related entities, see [Expand](http://docs.oasis-open.org/odata/odata/v4.01/odata-v4.01-part1-protocol.html#sec_SystemQueryOptionexpand)", "explode": false, "in": "query", "name": "$expand", "schema": {"items": {"enum": ["*", "_product", "_country", "_salesOrganization", "_distributionChannel", "_division", "warranties", "classificationData", "_c4c"], "type": "string"}, "type": "array", "uniqueItems": true}}], "responses": {"200": {"description": "Retrieved equipment", "content": {"application/json": {"schema": {"properties": {"value": {"items": {"$ref": "#/components/schemas/sap.graph.Equipment"}, "type": "array"}}, "title": "Collection of Equipment", "type": "object"}}}}, "4XX": {"$ref": "#/components/responses/error"}}, "summary": "Retrieve a list of equipment.", "tags": ["Equipment"]}, "post": {"requestBody": {"content": {"application/json": {"schema": {"$ref": "#/components/schemas/sap.graph.Equipment-create"}}}, "description": "Equipment.", "required": true}, "responses": {"201": {"description": "Created equipment", "content": {"application/json": {"schema": {"$ref": "#/components/schemas/sap.graph.Equipment"}}}}, "4XX": {"$ref": "#/components/responses/error"}}, "summary": "Create a single equipment.", "tags": ["Equipment"]}}, "/sap.graph/Equipment/{id}": {"parameters": [{"in": "path", "name": "id", "required": true, "description": "Qualified identifier", "schema": {"type": "string", "example": "ABC"}}], "get": {"parameters": [{"description": "Select properties to be returned, see [Select](http://docs.oasis-open.org/odata/odata/v4.01/odata-v4.01-part1-protocol.html#sec_SystemQueryOptionselect)", "explode": false, "in": "query", "name": "$select", "schema": {"items": {"enum": ["id", "createdAt", "changedAt", "displayId", "name", "category", "validFrom", "validTo", "product", "serialNumber", "country", "region", "city", "postalCode", "street", "houseNumber", "additionalHouseNumber", "building", "floor", "room", "salesOrganization", "distributionChannel", "division", "salesOffice", "salesGroup"], "type": "string"}, "type": "array", "uniqueItems": true}}, {"description": "Expand related entities, see [Expand](http://docs.oasis-open.org/odata/odata/v4.01/odata-v4.01-part1-protocol.html#sec_SystemQueryOptionexpand)", "explode": false, "in": "query", "name": "$expand", "schema": {"items": {"enum": ["*", "_product", "_country", "_salesOrganization", "_distributionChannel", "_division", "warranties", "classificationData", "_c4c"], "type": "string"}, "type": "array", "uniqueItems": true}}], "responses": {"200": {"description": "Retrieved equipment", "content": {"application/json": {"schema": {"$ref": "#/components/schemas/sap.graph.Equipment"}}}}, "4XX": {"$ref": "#/components/responses/error"}}, "summary": "Retrieve a single equipment.", "tags": ["Equipment"]}, "patch": {"requestBody": {"content": {"application/json": {"schema": {"$ref": "#/components/schemas/sap.graph.Equipment-update"}}}, "description": "Equipment.", "required": true}, "responses": {"204": {"description": "Success"}, "4XX": {"$ref": "#/components/responses/error"}}, "summary": "Change a single equipment.", "tags": ["Equipment"]}, "delete": {"responses": {"204": {"description": "Success"}, "4XX": {"$ref": "#/components/responses/error"}}, "summary": "Delete a single equipment.", "tags": ["Equipment"]}}, "/sap.graph/Equipment/{id}/warranties": {"parameters": [{"in": "path", "name": "id", "required": true, "description": "Qualified identifier", "schema": {"type": "string", "example": "ABC"}}], "get": {"parameters": [{"$ref": "#/components/parameters/top"}, {"$ref": "#/components/parameters/skip"}, {"$ref": "#/components/parameters/search"}, {"in": "query", "name": "$filter", "schema": {"type": "string"}, "description": "Filter items by property values, see [Filtering](http://docs.oasis-open.org/odata/odata/v4.01/odata-v4.01-part1-protocol.html#sec_SystemQueryOptionfilter)"}, {"$ref": "#/components/parameters/count"}, {"description": "Order items by property values, see [Sorting](http://docs.oasis-open.org/odata/odata/v4.01/odata-v4.01-part1-protocol.html#sec_SystemQueryOptionorderby)", "explode": false, "in": "query", "name": "$orderby", "schema": {"items": {"enum": ["warrantyType", "warrantyType desc", "warrantyId", "warrantyId desc", "startDate", "startDate desc", "endDate", "endDate desc"], "type": "string"}, "type": "array", "uniqueItems": true}}, {"description": "Select properties to be returned, see [Select](http://docs.oasis-open.org/odata/odata/v4.01/odata-v4.01-part1-protocol.html#sec_SystemQueryOptionselect)", "explode": false, "in": "query", "name": "$select", "schema": {"items": {"enum": ["warrantyType", "warrantyId", "startDate", "endDate"], "type": "string"}, "type": "array", "uniqueItems": true}}], "responses": {"200": {"description": "Retrieved warranties", "content": {"application/json": {"schema": {"properties": {"value": {"items": {"$ref": "#/components/schemas/sap.graph.Equipment_warranties"}, "type": "array"}}, "title": "Collection of Equipment_warranties", "type": "object"}}}}, "4XX": {"$ref": "#/components/responses/error"}}, "summary": "Retrieve a list of warranties of an equipment.", "tags": ["Equipment"]}, "post": {"requestBody": {"content": {"application/json": {"schema": {"$ref": "#/components/schemas/sap.graph.Equipment_warranties-create"}}}, "description": "New warranty", "required": true}, "responses": {"201": {"description": "Created warranty", "content": {"application/json": {"schema": {"$ref": "#/components/schemas/sap.graph.Equipment_warranties"}}}}, "4XX": {"$ref": "#/components/responses/error"}}, "summary": "Create a single warranty of an equipment.", "tags": ["Equipment"]}}, "/sap.graph/Equipment/{id}/warranties/{warrantyType-1}": {"parameters": [{"in": "path", "name": "id", "required": true, "description": "Qualified identifier", "schema": {"type": "string", "example": "ABC"}}, {"in": "path", "name": "warrantyType-1", "required": true, "description": "Warranty type.", "schema": {"type": "string", "example": "ABC"}}], "get": {"parameters": [{"description": "Select properties to be returned, see [Select](http://docs.oasis-open.org/odata/odata/v4.01/odata-v4.01-part1-protocol.html#sec_SystemQueryOptionselect)", "explode": false, "in": "query", "name": "$select", "schema": {"items": {"enum": ["warrantyType", "warrantyId", "startDate", "endDate"], "type": "string"}, "type": "array", "uniqueItems": true}}], "responses": {"200": {"description": "Retrieved warranty", "content": {"application/json": {"schema": {"$ref": "#/components/schemas/sap.graph.Equipment_warranties"}}}}, "4XX": {"$ref": "#/components/responses/error"}}, "summary": "Retrieve a single warranty of an equipment.", "tags": ["Equipment"]}, "patch": {"requestBody": {"content": {"application/json": {"schema": {"$ref": "#/components/schemas/sap.graph.Equipment_warranties-update"}}}, "description": "New property values", "required": true}, "responses": {"204": {"description": "Success"}, "4XX": {"$ref": "#/components/responses/error"}}, "summary": "Change a single warranty of an equipment.", "tags": ["Equipment"]}, "delete": {"responses": {"204": {"description": "Success"}, "4XX": {"$ref": "#/components/responses/error"}}, "summary": "Delete a single warranty of an equipment.", "tags": ["Equipment"]}}, "/sap.graph/Equipment/{id}/classificationData": {"parameters": [{"in": "path", "name": "id", "required": true, "description": "Qualified identifier", "schema": {"type": "string", "example": "ABC"}}], "get": {"parameters": [{"$ref": "#/components/parameters/top"}, {"$ref": "#/components/parameters/skip"}, {"$ref": "#/components/parameters/search"}, {"in": "query", "name": "$filter", "schema": {"type": "string"}, "description": "Filter items by property values, see [Filtering](http://docs.oasis-open.org/odata/odata/v4.01/odata-v4.01-part1-protocol.html#sec_SystemQueryOptionfilter)"}, {"$ref": "#/components/parameters/count"}, {"description": "Order items by property values, see [Sorting](http://docs.oasis-open.org/odata/odata/v4.01/odata-v4.01-part1-protocol.html#sec_SystemQueryOptionorderby)", "explode": false, "in": "query", "name": "$orderby", "schema": {"items": {"enum": ["id", "id desc", "class", "class desc", "classType", "classType desc", "characteristic", "characteristic desc", "characteristicValue", "characteristicValue desc"], "type": "string"}, "type": "array", "uniqueItems": true}}, {"description": "Select properties to be returned, see [Select](http://docs.oasis-open.org/odata/odata/v4.01/odata-v4.01-part1-protocol.html#sec_SystemQueryOptionselect)", "explode": false, "in": "query", "name": "$select", "schema": {"items": {"enum": ["id", "class", "classType", "characteristic", "characteristicValue"], "type": "string"}, "type": "array", "uniqueItems": true}}], "responses": {"200": {"description": "Retrieved classification data", "content": {"application/json": {"schema": {"properties": {"value": {"items": {"$ref": "#/components/schemas/sap.graph.Equipment_classificationData"}, "type": "array"}}, "title": "Collection of Equipment_classificationData", "type": "object"}}}}, "4XX": {"$ref": "#/components/responses/error"}}, "summary": "Retrieve a list of classification data of an equipment.", "tags": ["Equipment"]}, "post": {"requestBody": {"content": {"application/json": {"schema": {"$ref": "#/components/schemas/sap.graph.Equipment_classificationData-create"}}}, "description": "New classification datum", "required": true}, "responses": {"201": {"description": "Created classification datum", "content": {"application/json": {"schema": {"$ref": "#/components/schemas/sap.graph.Equipment_classificationData"}}}}, "4XX": {"$ref": "#/components/responses/error"}}, "summary": "Create a single classification datum of an equipment.", "tags": ["Equipment"]}}, "/sap.graph/Equipment/{id}/classificationData/{id-1}": {"parameters": [{"in": "path", "name": "id", "required": true, "description": "Qualified identifier", "schema": {"type": "string", "example": "ABC"}}, {"in": "path", "name": "id-1", "required": true, "description": "Identifier", "schema": {"type": "string", "example": "ABC"}}], "get": {"parameters": [{"description": "Select properties to be returned, see [Select](http://docs.oasis-open.org/odata/odata/v4.01/odata-v4.01-part1-protocol.html#sec_SystemQueryOptionselect)", "explode": false, "in": "query", "name": "$select", "schema": {"items": {"enum": ["id", "class", "classType", "characteristic", "characteristicValue"], "type": "string"}, "type": "array", "uniqueItems": true}}], "responses": {"200": {"description": "Retrieved classification datum", "content": {"application/json": {"schema": {"$ref": "#/components/schemas/sap.graph.Equipment_classificationData"}}}}, "4XX": {"$ref": "#/components/responses/error"}}, "summary": "Retrieve a single classification datum of an equipment.", "tags": ["Equipment"]}, "patch": {"requestBody": {"content": {"application/json": {"schema": {"$ref": "#/components/schemas/sap.graph.Equipment_classificationData-update"}}}, "description": "New property values", "required": true}, "responses": {"204": {"description": "Success"}, "4XX": {"$ref": "#/components/responses/error"}}, "summary": "Change a single classification datum of an equipment.", "tags": ["Equipment"]}, "delete": {"responses": {"204": {"description": "Success"}, "4XX": {"$ref": "#/components/responses/error"}}, "summary": "Delete a single classification datum of an equipment.", "tags": ["Equipment"]}}, "/$batch": {"post": {"description": "Group multiple requests into a single request payload, see [Batch Requests](http://docs.oasis-open.org/odata/odata/v4.01/odata-v4.01-part1-protocol.html#sec_BatchRequests).\n\n*Please note that \"Try it out\" is not supported for this request.*", "requestBody": {"content": {"multipart/mixed;boundary=request-separator": {"example": "--request-separator\nContent-Type: application/http\nContent-Transfer-Encoding: binary\n\nGET Bank HTTP/1.1\nAccept: application/json\n\n\n--request-separator--", "schema": {"type": "string"}}}, "description": "Batch request", "required": true}, "responses": {"200": {"content": {"multipart/mixed": {"example": "--response-separator\nContent-Type: application/http\n\nHTTP/1.1 200 OK\nContent-Type: application/json\n\n{...}\n--response-separator--", "schema": {"type": "string"}}}, "description": "Batch response"}, "4XX": {"$ref": "#/components/responses/error"}}, "summary": "Send a group of requests", "tags": ["Batch Requests"]}}}, "security": [{"bearerAuth": []}]}